{"Canada": 33, "Serbia and Montenegro": 186, "Cameroon": 32, "Burkina Faso": 233, "Russian Federation": 185, "Dominica": 55, "Tajikistan": 208, "Turkey": 223, "199": "Slovakia", "198": "Slovenia", "195": "Senegal", "194": "Saudi Arabia", "197": "Sierra Leone", "191": "Saint Vincent and the Grenadines", "193": "Sao Tome and Principe", "Slovakia": 199, "Norway": 162, "United States of America": 231, "Libya": 124, "5009": "Total FAO", "Finland": 67, "Central African Republic": 37, "108": "Kazakhstan", "109": "Jamaica", "Wake Island": 242, "102": "Iran (Islamic Republic of)", "103": "Iraq", "100": "India", "101": "Indonesia", "106": "Italy", "107": "C\u00f4te d'Ivoire", "104": "Ireland", "105": "Israel", "39": "Chad", "38": "Sri Lanka", "Portugal": 174, "33": "Canada", "32": "Cameroon", "37": "Central African Republic", "35": "Cabo Verde", "Kuwait": 118, "Mali": 133, "Costa Rica": 48, "Nigeria": 159, "Ecuador": 58, "Australia": 10, "Lao People's Democratic Republic": 120, "Belgium-Luxembourg": 15, "Denmark": 54, "Philippines": 171, "99": "Iceland", "98": "Croatia", "Sz\u00e9kelyf\u00f6ld": 999, "United Republic of Tanzania": 215, "91": "Guyana", "90": "Guinea", "93": "Haiti", "95": "Honduras", "97": "Hungary", "Estonia": 63, "Lebanon": 121, "Republic of Korea": 117, "Colombia": 44, "Nepal": 149, "238": "Ethiopia", "Suriname": 207, "234": "Uruguay", "235": "Uzbekistan", "236": "Venezuela (Bolivarian Republic of)", "237": "Viet Nam", "230": "Ukraine", "231": "United States of America", "233": "Burkina Faso", "1": "Armenia", "Jordan": 112, "146": "Republic of Moldova", "Eritrea": 178, "144": "Mozambique", "143": "Morocco", "141": "Mongolia", "149": "Nepal", "C\u00f4te d'Ivoire": 107, "Mexico": 138, "Democratic People's Republic of Korea": 116, "Greece": 84, "Sao Tome and Principe": 193, "133": "Mali", "131": "Malaysia", "130": "Malawi", "137": "Mauritius", "136": "Mauritania", "135": "Martinique", "134": "Malta", "138": "Mexico", "Ghana": 81, "25": "Solomon Islands", "26": "Brunei Darussalam", "27": "Bulgaria", "21": "Brazil", "23": "Belize", "28": "Myanmar", "29": "Burundi", "Guatemala": 89, "Spain": 203, "Oman": 221, "Cabo Verde": 35, "Gabon": 74, "United Arab Emirates": 225, "India": 100, "Lesotho": 122, "Kenya": 114, "Czech Republic": 167, "Iran (Islamic Republic of)": 102, "French Polynesia": 70, "89": "Guatemala", "Peru": 170, "80": "Bosnia and Herzegovina", "81": "Ghana", "87": "Guadeloupe", "84": "Greece", "Benin": 53, "China": 351, "7": "Angola", "Bolivia (Plurinational State of)": 19, "Ukraine": 230, "Tonga": 219, "Indonesia": 101, "Mauritius": 137, "244": "Samoa", "242": "Wake Island", "249": "Yemen", "Bulgaria": 27, "Angola": 7, "Chad": 39, "South Africa": 202, "Brunei Darussalam": 26, "Senegal": 195, "Uganda": 226, "Hungary": 97, "Niger": 158, "Brazil": 21, "Republic of Moldova": 146, "179": "Qatar", "178": "Eritrea", "176": "Timor-Leste", "175": "Guinea-Bissau", "174": "Portugal", "173": "Poland", "171": "Philippines", "170": "Peru", "203": "Spain", "Algeria": 4, "182": "R\u00e9union", "183": "Romania", "181": "Zimbabwe", "186": "Serbia and Montenegro", "184": "Rwanda", "185": "Russian Federation", "Belgium": 255, "Haiti": 93, "Iraq": 103, "Unspecified Area": 252, "Gambia": 75, "60": "El Salvador", "Guinea-Bissau": 175, "11": "Austria", "10": "Australia", "Venezuela (Bolivarian Republic of)": 236, "12": "Bahamas", "15": "Belgium-Luxembourg", "14": "Barbados", "16": "Bangladesh", "19": "Bolivia (Plurinational State of)", "18": "Bhutan", "Equatorial Guinea": 61, "Djibouti": 72, "Timor-Leste": 176, "Nicaragua": 157, "Democratic Republic of the Congo": 250, "R\u00e9union": 182, "Iceland": 99, "Zambia": 251, "Germany": 79, "Kazakhstan": 108, "201": "Somalia", "200": "Singapore", "Kyrgyzstan": 113, "202": "South Africa", "207": "Suriname", "206": "Sudan (former)", "208": "Tajikistan", "75": "Gambia", "74": "Gabon", "73": "Georgia", "72": "Djibouti", "Guyana": 91, "79": "Germany", "2": "Afghanistan", "Honduras": 95, "Egypt": 59, "Sudan (former)": 206, "Turkmenistan": 213, "Ethiopia": 238, "Bosnia and Herzegovina": 80, "68": "France", "Liberia": 123, "Netherlands": 150, "999": "Sz\u00e9kelyf\u00f6ld", "13": "Bahrain", "120": "Lao People's Democratic Republic", "121": "Lebanon", "122": "Lesotho", "123": "Liberia", "124": "Libya", "126": "Lithuania", "129": "Madagascar", "Afghanistan": 2, "France": 68, "Vanuatu": 155, "Malawi": 130, "3": "Albania", "Dominican Republic": 56, "Saudi Arabia": 194, "Malaysia": 131, "Guinea": 90, "Panama": 166, "Luxembourg": 256, "Bahamas": 12, "61": "Equatorial Guinea", "63": "Estonia", "Ireland": 104, "67": "Finland", "252": "Unspecified Area", "69": "French Guiana", "250": "Democratic Republic of the Congo", "251": "Zambia", "256": "Luxembourg", "254": "Others (adjustment)", "255": "Belgium", "Bhutan": 18, "El Salvador": 60, "Thailand": 216, "Belize": 23, "Sierra Leone": 197, "Georgia": 73, "Poland": 173, "168": "Papua New Guinea", "169": "Paraguay", "165": "Pakistan", "166": "Panama", "167": "Czech Republic", "162": "Norway", "Uzbekistan": 235, "Fiji": 66, "Barbados": 14, "Madagascar": 129, "Italy": 106, "Israel": 105, "Papua New Guinea": 168, "Zimbabwe": 181, "Martinique": 135, "9": "Argentina", "Mauritania": 136, "Trinidad and Tobago": 220, "Latvia": 119, "Guadeloupe": 87, "United Kingdom": 229, "Congo": 46, "351": "China", "Paraguay": 169, "216": "Thailand", "217": "Togo", "215": "United Republic of Tanzania", "212": "Syrian Arab Republic", "213": "Turkmenistan", "210": "Sweden", "211": "Switzerland", "Lithuania": 126, "Cambodia": 115, "219": "Tonga", "Argentina": 9, "Bahrain": 13, "Slovenia": 198, "4": "Algeria", "Pakistan": 165, "French Guiana": 69, "Samoa": 244, "New Zealand": 156, "Yemen": 249, "Jamaica": 109, "Albania": 3, "59": "Egypt", "58": "Ecuador", "55": "Dominica", "54": "Denmark", "57": "Belarus", "56": "Dominican Republic", "Viet Nam": 237, "50": "Cyprus", "53": "Benin", "52": "Azerbaijan", "Saint Vincent and the Grenadines": 191, "66": "Fiji", "Netherlands Antilles (former)": 151, "Cyprus": 50, "Azerbaijan": 52, "115": "Cambodia", "114": "Kenya", "117": "Republic of Korea", "Rwanda": 184, "110": "Japan", "113": "Kyrgyzstan", "112": "Jordan", "119": "Latvia", "118": "Kuwait", "Cuba": 49, "Togo": 217, "Armenia": 1, "Total FAO": 5009, "Sweden": 210, "Romania": 183, "Qatar": 179, "Austria": 11, "Mozambique": 144, "Japan": 110, "70": "French Polynesia", "Bangladesh": 16, "Belarus": 57, "Solomon Islands": 25, "Chile": 40, "Croatia": 98, "Mongolia": 141, "229": "United Kingdom", "Switzerland": 211, "226": "Uganda", "225": "United Arab Emirates", "223": "Turkey", "222": "Tunisia", "221": "Oman", "220": "Trinidad and Tobago", "Uruguay": 234, "Syrian Arab Republic": 212, "116": "Democratic People's Republic of Korea", "Burundi": 29, "Somalia": 201, "151": "Netherlands Antilles (former)", "150": "Netherlands", "153": "New Caledonia", "155": "Vanuatu", "157": "Nicaragua", "156": "New Zealand", "159": "Nigeria", "158": "Niger", "Malta": 134, "48": "Costa Rica", "49": "Cuba", "46": "Congo", "44": "Colombia", "40": "Chile", "New Caledonia": 153, "Others (adjustment)": 254, "Myanmar": 28, "Morocco": 143, "Tunisia": 222, "Singapore": 200, "Sri Lanka": 38}